[{"MatchID":2067745196,"Lane":"BOTTOM","Role":"DUO_SUPPORT","Kills":4,"Deaths":0,"Assists":17,"GoldEarned":9888,"Winner":true,"GameDuration":1606},{"MatchID":2067759427,"Lane":"BOTTOM","Role":"DUO_SUPPORT","Kills":1,"Deaths":1,"Assists":16,"GoldEarned":7127,"Winner":true,"GameDuration":1247},{"MatchID":2071223601,"Lane":"TOP","Role":"SOLO","Kills":11,"Deaths":7,"Assists":10,"GoldEarned":14572,"Winner":true,"GameDuration":1814},{"MatchID":2072040039,"Lane":"MIDDLE","Role":"SOLO","Kills":5,"Deaths":5,"Assists":7,"GoldEarned":11777,"Winner":true,"GameDuration":1772},{"MatchID":2073201887,"Lane":"BOTTOM","Role":"DUO_CARRY","Kills":2,"Deaths":4,"Assists":4,"GoldEarned":10318,"Winner":false,"GameDuration":1716},{"MatchID":2080011411,"Lane":"TOP","Role":"DUO_CARRY","Kills":5,"Deaths":3,"Assists":12,"GoldEarned":13988,"Winner":true,"GameDuration":1876},{"MatchID":2084071419,"Lane":"BOTTOM","Role":"DUO_SUPPORT","Kills":0,"Deaths":8,"Assists":7,"GoldEarned":6878,"Winner":false,"GameDuration":1620},{"MatchID":2084149136,"Lane":"BOTTOM","Role":"DUO_SUPPORT","Kills":2,"Deaths":3,"Assists":7,"GoldEarned":6918,"Winner":false,"GameDuration":1531},{"MatchID":2085296956,"Lane":"BOTTOM","Role":"DUO_SUPPORT","Kills":4,"Deaths":4,"Assists":8,"GoldEarned":9062,"Winner":false,"GameDuration":1667},{"MatchID":2092982180,"Lane":"BOTTOM","Role":"DUO_SUPPORT","Kills":1,"Deaths":7,"Assists":9,"GoldEarned":7236,"Winner":false,"GameDuration":1836},{"MatchID":2094552794,"Lane":"BOTTOM","Role":"DUO_SUPPORT","Kills":1,"Deaths":3,"Assists":10,"GoldEarned":5733,"Winner":false,"GameDuration":1331},{"MatchID":2095701212,"Lane":"BOTTOM","Role":"DUO_SUPPORT","Kills":2,"Deaths":6,"Assists":10,"GoldEarned":8897,"Winner":false,"GameDuration":2026},{"MatchID":2097001481,"Lane":"BOTTOM","Role":"DUO_SUPPORT","Kills":0,"Deaths":2,"Assists":12,"GoldEarned":11079,"Winner":true,"GameDuration":2167},{"MatchID":2097016738,"Lane":"BOTTOM","Role":"DUO_SUPPORT","Kills":4,"Deaths":0,"Assists":6,"GoldEarned":7660,"Winner":true,"GameDuration":1244},{"MatchID":2097336010,"Lane":"BOTTOM","Role":"DUO_SUPPORT","Kills":2,"Deaths":0,"Assists":3,"GoldEarned":5896,"Winner":false,"GameDuration":1262},{"MatchID":2098064785,"Lane":"TOP","Role":"SOLO","Kills":2,"Deaths":4,"Assists":11,"GoldEarned":10587,"Winner":true,"GameDuration":1464},{"MatchID":2098431158,"Lane":"BOTTOM","Role":"DUO_SUPPORT","Kills":1,"Deaths":9,"Assists":22,"GoldEarned":14807,"Winner":false,"GameDuration":3095},{"MatchID":2098805496,"Lane":"BOTTOM","Role":"DUO_SUPPORT","Kills":2,"Deaths":3,"Assists":17,"GoldEarned":10971,"Winner":true,"GameDuration":2036},{"MatchID":2098812271,"Lane":"BOTTOM","Role":"DUO_SUPPORT","Kills":3,"Deaths":4,"Assists":5,"GoldEarned":6567,"Winner":false,"GameDuration":1427},{"MatchID":2098953407,"Lane":"BOTTOM","Role":"DUO_SUPPORT","Kills":6,"Deaths":2,"Assists":13,"GoldEarned":10895,"Winner":true,"GameDuration":1773},{"MatchID":2100382034,"Lane":"BOTTOM","Role":"DUO_SUPPORT","Kills":2,"Deaths":0,"Assists":8,"GoldEarned":6126,"Winner":true,"GameDuration":1216},{"MatchID":2100606466,"Lane":"BOTTOM","Role":"DUO_SUPPORT","Kills":0,"Deaths":1,"Assists":1,"GoldEarned":3344,"Winner":false,"GameDuration":939},{"MatchID":2100837915,"Lane":"BOTTOM","Role":"DUO_SUPPORT","Kills":5,"Deaths":3,"Assists":14,"GoldEarned":12173,"Winner":true,"GameDuration":1910},{"MatchID":2102050058,"Lane":"BOTTOM","Role":"DUO_SUPPORT","Kills":0,"Deaths":3,"Assists":19,"GoldEarned":7509,"Winner":true,"GameDuration":1396},{"MatchID":2102128140,"Lane":"TOP","Role":"SOLO","Kills":5,"Deaths":6,"Assists":11,"GoldEarned":13661,"Winner":true,"GameDuration":1886},{"MatchID":2102181282,"Lane":"TOP","Role":"SOLO","Kills":4,"Deaths":7,"Assists":7,"GoldEarned":12194,"Winner":false,"GameDuration":1998},{"MatchID":2106790163,"Lane":"BOTTOM","Role":"DUO_SUPPORT","Kills":1,"Deaths":1,"Assists":3,"GoldEarned":4438,"Winner":false,"GameDuration":1119},{"MatchID":2109779701,"Lane":"BOTTOM","Role":"DUO_SUPPORT","Kills":2,"Deaths":5,"Assists":7,"GoldEarned":7624,"Winner":false,"GameDuration":1548},{"MatchID":2110781487,"Lane":"BOTTOM","Role":"DUO_SUPPORT","Kills":0,"Deaths":4,"Assists":1,"GoldEarned":4487,"Winner":false,"GameDuration":1238},{"MatchID":2110820369,"Lane":"BOTTOM","Role":"DUO_SUPPORT","Kills":0,"Deaths":5,"Assists":26,"GoldEarned":12706,"Winner":true,"GameDuration":2489},{"MatchID":2112723133,"Lane":"BOTTOM","Role":"DUO_SUPPORT","Kills":0,"Deaths":1,"Assists":22,"GoldEarned":12428,"Winner":true,"GameDuration":2207},{"MatchID":2117613999,"Lane":"BOTTOM","Role":"DUO_SUPPORT","Kills":0,"Deaths":5,"Assists":10,"GoldEarned":8822,"Winner":false,"GameDuration":2144},{"MatchID":2117678862,"Lane":"BOTTOM","Role":"DUO_SUPPORT","Kills":0,"Deaths":2,"Assists":20,"GoldEarned":9301,"Winner":true,"GameDuration":1777},{"MatchID":2117681013,"Lane":"BOTTOM","Role":"DUO_SUPPORT","Kills":3,"Deaths":5,"Assists":16,"GoldEarned":12548,"Winner":true,"GameDuration":2233},{"MatchID":2119367259,"Lane":"BOTTOM","Role":"DUO_SUPPORT","Kills":1,"Deaths":4,"Assists":8,"GoldEarned":7257,"Winner":false,"GameDuration":1666},{"MatchID":2120113004,"Lane":"BOTTOM","Role":"DUO_SUPPORT","Kills":0,"Deaths":3,"Assists":7,"GoldEarned":6861,"Winner":false,"GameDuration":1664},{"MatchID":2123104439,"Lane":"BOTTOM","Role":"DUO_SUPPORT","Kills":1,"Deaths":6,"Assists":19,"GoldEarned":10533,"Winner":false,"GameDuration":2145},{"MatchID":2123276257,"Lane":"TOP","Role":"SOLO","Kills":1,"Deaths":4,"Assists":2,"GoldEarned":7546,"Winner":false,"GameDuration":1452},{"MatchID":2126433962,"Lane":"BOTTOM","Role":"DUO_SUPPORT","Kills":3,"Deaths":2,"Assists":10,"GoldEarned":6812,"Winner":true,"GameDuration":1285},{"MatchID":2129362190,"Lane":"BOTTOM","Role":"DUO_SUPPORT","Kills":3,"Deaths":4,"Assists":7,"GoldEarned":8020,"Winner":false,"GameDuration":1639},{"MatchID":2130266295,"Lane":"BOTTOM","Role":"DUO_SUPPORT","Kills":0,"Deaths":4,"Assists":1,"GoldEarned":4799,"Winner":false,"GameDuration":1289},{"MatchID":2135216256,"Lane":"MIDDLE","Role":"SOLO","Kills":3,"Deaths":8,"Assists":6,"GoldEarned":12476,"Winner":false,"GameDuration":2222}]