[{"MatchID":2067611057,"Lane":"TOP","Role":"SOLO","Kills":3,"Deaths":4,"Assists":5,"GoldEarned":10727,"Winner":true,"GameDuration":1654},{"MatchID":2068146032,"Lane":"TOP","Role":"SOLO","Kills":5,"Deaths":5,"Assists":12,"GoldEarned":16750,"Winner":true,"GameDuration":2653},{"MatchID":2068249746,"Lane":"TOP","Role":"SOLO","Kills":2,"Deaths":2,"Assists":10,"GoldEarned":8929,"Winner":true,"GameDuration":1372},{"MatchID":2068251270,"Lane":"TOP","Role":"SOLO","Kills":11,"Deaths":1,"Assists":7,"GoldEarned":13819,"Winner":true,"GameDuration":1742},{"MatchID":2069053990,"Lane":"TOP","Role":"SOLO","Kills":7,"Deaths":4,"Assists":5,"GoldEarned":14410,"Winner":false,"GameDuration":2279},{"MatchID":2069146662,"Lane":"TOP","Role":"SOLO","Kills":1,"Deaths":0,"Assists":5,"GoldEarned":10186,"Winner":true,"GameDuration":1501},{"MatchID":2069147642,"Lane":"TOP","Role":"SOLO","Kills":4,"Deaths":1,"Assists":12,"GoldEarned":13329,"Winner":true,"GameDuration":1717},{"MatchID":2069148846,"Lane":"TOP","Role":"SOLO","Kills":4,"Deaths":3,"Assists":10,"GoldEarned":9483,"Winner":true,"GameDuration":1463},{"MatchID":2071112064,"Lane":"TOP","Role":"SOLO","Kills":7,"Deaths":0,"Assists":7,"GoldEarned":13096,"Winner":true,"GameDuration":1909},{"MatchID":2072737719,"Lane":"TOP","Role":"SOLO","Kills":4,"Deaths":2,"Assists":9,"GoldEarned":11788,"Winner":true,"GameDuration":1606},{"MatchID":2080292969,"Lane":"TOP","Role":"SOLO","Kills":2,"Deaths":0,"Assists":4,"GoldEarned":8322,"Winner":true,"GameDuration":1223},{"MatchID":2080309329,"Lane":"TOP","Role":"SOLO","Kills":10,"Deaths":5,"Assists":6,"GoldEarned":18697,"Winner":false,"GameDuration":2507},{"MatchID":2087484006,"Lane":"TOP","Role":"SOLO","Kills":6,"Deaths":5,"Assists":2,"GoldEarned":10873,"Winner":false,"GameDuration":1742},{"MatchID":2097902720,"Lane":"TOP","Role":"SOLO","Kills":2,"Deaths":4,"Assists":3,"GoldEarned":8171,"Winner":false,"GameDuration":1614},{"MatchID":2101916382,"Lane":"TOP","Role":"SOLO","Kills":7,"Deaths":5,"Assists":10,"GoldEarned":17122,"Winner":false,"GameDuration":2551},{"MatchID":2101925177,"Lane":"TOP","Role":"SOLO","Kills":5,"Deaths":3,"Assists":7,"GoldEarned":11636,"Winner":true,"GameDuration":1590},{"MatchID":2102040752,"Lane":"MIDDLE","Role":"SOLO","Kills":6,"Deaths":8,"Assists":14,"GoldEarned":15250,"Winner":false,"GameDuration":2260},{"MatchID":2108686186,"Lane":"TOP","Role":"SOLO","Kills":8,"Deaths":5,"Assists":4,"GoldEarned":13373,"Winner":false,"GameDuration":1979},{"MatchID":2131764834,"Lane":"TOP","Role":"SOLO","Kills":5,"Deaths":0,"Assists":6,"GoldEarned":12232,"Winner":true,"GameDuration":1603},{"MatchID":2132571411,"Lane":"TOP","Role":"SOLO","Kills":3,"Deaths":3,"Assists":10,"GoldEarned":11937,"Winner":true,"GameDuration":1573},{"MatchID":2132695193,"Lane":"TOP","Role":"SOLO","Kills":3,"Deaths":2,"Assists":7,"GoldEarned":10533,"Winner":true,"GameDuration":1553},{"MatchID":2133050998,"Lane":"TOP","Role":"SOLO","Kills":6,"Deaths":0,"Assists":6,"GoldEarned":10983,"Winner":true,"GameDuration":1235},{"MatchID":2134923204,"Lane":"TOP","Role":"SOLO","Kills":2,"Deaths":2,"Assists":8,"GoldEarned":10628,"Winner":true,"GameDuration":1605},{"MatchID":2135103774,"Lane":"TOP","Role":"SOLO","Kills":3,"Deaths":1,"Assists":4,"GoldEarned":8232,"Winner":true,"GameDuration":1086},{"MatchID":2135543635,"Lane":"TOP","Role":"SOLO","Kills":5,"Deaths":0,"Assists":4,"GoldEarned":8514,"Winner":true,"GameDuration":1212}]