[{"MatchID":2089153540,"Lane":"TOP","Role":"SOLO","FrameInterval":60000,"Frames":[{"Type":"Kill","Location":[2078,12982]},{"Type":"Kill","Location":[1255,10628]},{"Type":"Kill","Location":[724,7708]},{"Type":"Kill","Location":[1818,11088]}]},{"MatchID":2089168116,"Lane":"TOP","Role":"SOLO","FrameInterval":60000,"Frames":[{"Type":"Kill","Location":[3506,13714]},{"Type":"Kill","Location":[3878,13833]},{"Type":"Kill","Location":[3225,13737]},{"Type":"Death","Location":[1637,12640]},{"Type":"Death","Location":[13778,3710]},{"Type":"Kill","Location":[5141,13472]},{"Type":"Death","Location":[6397,12659]},{"Type":"Death","Location":[3763,11040]},{"Type":"Kill","Location":[7130,13418]},{"Type":"Death","Location":[9831,13680]},{"Type":"Kill","Location":[4596,9506]},{"Type":"Kill","Location":[4836,9401]},{"Type":"Kill","Location":[12878,10722]}]},{"MatchID":2089285506,"Lane":"TOP","Role":"SOLO","FrameInterval":60000,"Frames":[{"Type":"Death","Location":[1443,12463]},{"Type":"Death","Location":[2809,13403]},{"Type":"Kill","Location":[6234,8964]},{"Type":"Kill","Location":[5734,8608]},{"Type":"Death","Location":[5433,8739]},{"Type":"Kill","Location":[1828,12762]},{"Type":"Kill","Location":[2209,12224]},{"Type":"Death","Location":[4604,10031]},{"Type":"Kill","Location":[5032,5874]},{"Type":"Kill","Location":[8353,8886]},{"Type":"Death","Location":[8543,8823]},{"Type":"Death","Location":[5279,10581]},{"Type":"Kill","Location":[2252,7598]}]},{"MatchID":2089289357,"Lane":"TOP","Role":"SOLO","FrameInterval":60000,"Frames":[{"Type":"Kill","Location":[12993,1910]},{"Type":"Kill","Location":[12843,3330]},{"Type":"Kill","Location":[13700,4830]},{"Type":"Death","Location":[13272,3355]},{"Type":"Kill","Location":[4084,12716]},{"Type":"Kill","Location":[3890,13142]},{"Type":"Kill","Location":[10622,5260]},{"Type":"Death","Location":[11396,5882]},{"Type":"Kill","Location":[5354,12565]},{"Type":"Kill","Location":[1776,11086]},{"Type":"Kill","Location":[13821,8123]},{"Type":"Death","Location":[12478,5218]},{"Type":"Death","Location":[11265,12738]},{"Type":"Death","Location":[8646,12904]}]},{"MatchID":2089303208,"Lane":"TOP","Role":"SOLO","FrameInterval":60000,"Frames":[{"Type":"Kill","Location":[2902,7538]},{"Type":"Kill","Location":[1201,9870]},{"Type":"Kill","Location":[6392,6072]},{"Type":"Kill","Location":[12872,2654]},{"Type":"Kill","Location":[1188,2107]}]},{"MatchID":2089731665,"Lane":"TOP","Role":"SOLO","FrameInterval":60000,"Frames":[{"Type":"Death","Location":[2081,11805]},{"Type":"Kill","Location":[2542,11722]},{"Type":"Kill","Location":[810,9727]},{"Type":"Death","Location":[771,9553]},{"Type":"Death","Location":[3061,13698]},{"Type":"Kill","Location":[1413,11129]},{"Type":"Death","Location":[12849,7355]}]},{"MatchID":2089746248,"Lane":"MIDDLE","Role":"SOLO","FrameInterval":60000,"Frames":[{"Type":"Death","Location":[8907,8133]},{"Type":"Death","Location":[8651,8121]},{"Type":"Kill","Location":[6832,7529]},{"Type":"Death","Location":[5315,10405]},{"Type":"Kill","Location":[1310,4157]},{"Type":"Kill","Location":[4440,5236]},{"Type":"Kill","Location":[4336,4465]}]},{"MatchID":2089807499,"Lane":"TOP","Role":"SOLO","FrameInterval":60000,"Frames":[{"Type":"Kill","Location":[1130,10468]},{"Type":"Death","Location":[1700,10928]},{"Type":"Kill","Location":[10812,1298]},{"Type":"Death","Location":[13369,2955]},{"Type":"Death","Location":[2858,6142]},{"Type":"Kill","Location":[7504,8006]},{"Type":"Death","Location":[6976,7370]},{"Type":"Death","Location":[12619,5720]},{"Type":"Death","Location":[4948,7926]},{"Type":"Kill","Location":[8726,9134]},{"Type":"Kill","Location":[10712,10474]},{"Type":"Death","Location":[11393,10823]},{"Type":"Kill","Location":[10820,10338]},{"Type":"Kill","Location":[12101,13522]},{"Type":"Kill","Location":[13695,13210]}]},{"MatchID":2089812158,"Lane":"MIDDLE","Role":"SOLO","FrameInterval":60000,"Frames":[{"Type":"Kill","Location":[7433,6858]},{"Type":"Kill","Location":[4290,4925]},{"Type":"Death","Location":[4869,5809]},{"Type":"Kill","Location":[4691,7520]},{"Type":"Kill","Location":[5879,7078]},{"Type":"Kill","Location":[4778,7091]},{"Type":"Death","Location":[6690,7606]},{"Type":"Kill","Location":[5442,6112]},{"Type":"Kill","Location":[8791,4289]},{"Type":"Kill","Location":[8888,4447]},{"Type":"Kill","Location":[7623,3905]},{"Type":"Death","Location":[6945,2927]},{"Type":"Kill","Location":[13517,5123]}]},{"MatchID":2089901989,"Lane":"TOP","Role":"SOLO","FrameInterval":60000,"Frames":[{"Type":"Death","Location":[1292,10296]},{"Type":"Death","Location":[1847,11793]},{"Type":"Death","Location":[4424,11869]},{"Type":"Kill","Location":[8197,10552]},{"Type":"Death","Location":[3195,10932]},{"Type":"Kill","Location":[8802,1103]},{"Type":"Kill","Location":[10163,10514]},{"Type":"Death","Location":[6493,8239]},{"Type":"Death","Location":[2960,11312]},{"Type":"Kill","Location":[14066,4224]},{"Type":"Kill","Location":[7794,8200]}]},{"MatchID":2089965008,"Lane":"TOP","Role":"SOLO","FrameInterval":60000,"Frames":[{"Type":"Kill","Location":[1445,12047]},{"Type":"Kill","Location":[1228,10623]},{"Type":"Death","Location":[3190,10549]},{"Type":"Kill","Location":[7706,1155]},{"Type":"Kill","Location":[4272,1960]},{"Type":"Kill","Location":[9012,6214]}]},{"MatchID":2089982141,"Lane":"TOP","Role":"SOLO","FrameInterval":60000,"Frames":[{"Type":"Kill","Location":[3643,12866]},{"Type":"Kill","Location":[826,10465]},{"Type":"Kill","Location":[3033,11871]},{"Type":"Kill","Location":[1192,10868]},{"Type":"Kill","Location":[1524,2340]},{"Type":"Death","Location":[2962,5398]},{"Type":"Kill","Location":[1344,6787]},{"Type":"Kill","Location":[1124,6720]},{"Type":"Kill","Location":[3128,6751]},{"Type":"Death","Location":[3447,6920]},{"Type":"Kill","Location":[2233,9013]},{"Type":"Kill","Location":[1530,4345]},{"Type":"Death","Location":[1060,3185]},{"Type":"Kill","Location":[6458,6168]},{"Type":"Kill","Location":[3501,8408]}]},{"MatchID":2090646097,"Lane":"TOP","Role":"SOLO","FrameInterval":60000,"Frames":[{"Type":"Death","Location":[12533,2217]},{"Type":"Kill","Location":[6500,13832]},{"Type":"Kill","Location":[9824,10423]},{"Type":"Kill","Location":[10297,12762]}]},{"MatchID":2090710735,"Lane":"TOP","Role":"SOLO","FrameInterval":60000,"Frames":[{"Type":"Kill","Location":[1180,10641]},{"Type":"Kill","Location":[1239,9835]},{"Type":"Death","Location":[6640,6700]},{"Type":"Kill","Location":[4644,1679]},{"Type":"Death","Location":[5185,1790]},{"Type":"Kill","Location":[11282,5853]},{"Type":"Death","Location":[2181,3859]},{"Type":"Kill","Location":[6732,7872]},{"Type":"Kill","Location":[2011,2795]},{"Type":"Death","Location":[2694,2672]}]},{"MatchID":2090725651,"Lane":"TOP","Role":"SOLO","FrameInterval":60000,"Frames":[{"Type":"Kill","Location":[4381,13540]},{"Type":"Death","Location":[4058,11640]},{"Type":"Kill","Location":[6351,7228]},{"Type":"Death","Location":[3753,13209]},{"Type":"Kill","Location":[4817,13477]},{"Type":"Death","Location":[8592,7581]},{"Type":"Kill","Location":[2903,9877]},{"Type":"Kill","Location":[9139,2107]},{"Type":"Kill","Location":[8277,745]},{"Type":"Kill","Location":[6551,8265]},{"Type":"Kill","Location":[8677,6438]},{"Type":"Kill","Location":[8330,6885]},{"Type":"Kill","Location":[8110,5686]},{"Type":"Kill","Location":[11194,10019]},{"Type":"Death","Location":[7286,8916]}]},{"MatchID":2090793244,"Lane":"TOP","Role":"SOLO","FrameInterval":60000,"Frames":[{"Type":"Kill","Location":[9590,840]},{"Type":"Death","Location":[10705,886]},{"Type":"Kill","Location":[8763,13911]},{"Type":"Kill","Location":[10445,10913]},{"Type":"Death","Location":[3678,8226]},{"Type":"Death","Location":[12418,13367]}]},{"MatchID":2091702924,"Lane":"TOP","Role":"SOLO","FrameInterval":60000,"Frames":[{"Type":"Death","Location":[907,11080]},{"Type":"Death","Location":[2963,12951]},{"Type":"Kill","Location":[6355,6247]},{"Type":"Kill","Location":[1567,4945]},{"Type":"Kill","Location":[3502,3411]},{"Type":"Kill","Location":[3944,7180]},{"Type":"Death","Location":[3925,3618]}]},{"MatchID":2095947090,"Lane":"TOP","Role":"SOLO","FrameInterval":60000,"Frames":[{"Type":"Kill","Location":[13646,3295]},{"Type":"Death","Location":[11880,3147]},{"Type":"Kill","Location":[4292,13700]},{"Type":"Kill","Location":[5978,11348]},{"Type":"Death","Location":[4970,11671]},{"Type":"Death","Location":[14064,4164]},{"Type":"Death","Location":[8563,840]}]},{"MatchID":2096295183,"Lane":"JUNGLE","Role":"NONE","FrameInterval":60000,"Frames":[{"Type":"Kill","Location":[5594,6062]},{"Type":"Kill","Location":[8421,5337]},{"Type":"Kill","Location":[8638,5874]},{"Type":"Kill","Location":[1536,3529]},{"Type":"Death","Location":[1906,3981]},{"Type":"Death","Location":[8008,913]},{"Type":"Kill","Location":[10457,9001]},{"Type":"Kill","Location":[5903,5817]}]},{"MatchID":2097010731,"Lane":"BOTTOM","Role":"DUO_CARRY","FrameInterval":60000,"Frames":[{"Type":"Kill","Location":[13073,3252]},{"Type":"Kill","Location":[13685,4326]},{"Type":"Death","Location":[13192,3534]},{"Type":"Death","Location":[8424,922]},{"Type":"Kill","Location":[13606,3932]},{"Type":"Death","Location":[10604,1584]},{"Type":"Kill","Location":[5476,5799]},{"Type":"Kill","Location":[6698,7043]},{"Type":"Death","Location":[7473,6834]},{"Type":"Kill","Location":[9730,5658]},{"Type":"Death","Location":[7602,4724]},{"Type":"Death","Location":[9950,6640]},{"Type":"Death","Location":[1720,6050]},{"Type":"Kill","Location":[4917,8596]},{"Type":"Kill","Location":[1373,5541]},{"Type":"Kill","Location":[860,5578]},{"Type":"Death","Location":[4534,10026]},{"Type":"Kill","Location":[9424,2433]},{"Type":"Kill","Location":[4756,3942]},{"Type":"Death","Location":[1368,6058]}]},{"MatchID":2097016086,"Lane":"TOP","Role":"SOLO","FrameInterval":60000,"Frames":[{"Type":"Kill","Location":[6684,13988]},{"Type":"Kill","Location":[1769,7994]},{"Type":"Death","Location":[1082,7990]},{"Type":"Kill","Location":[10786,1306]},{"Type":"Kill","Location":[9820,3276]},{"Type":"Kill","Location":[3818,10078]},{"Type":"Kill","Location":[7272,7598]},{"Type":"Kill","Location":[2818,4046]},{"Type":"Death","Location":[7765,7464]},{"Type":"Kill","Location":[7618,8185]},{"Type":"Kill","Location":[7452,7309]},{"Type":"Kill","Location":[7575,7559]},{"Type":"Death","Location":[7122,7553]}]},{"MatchID":2101136909,"Lane":"TOP","Role":"SOLO","FrameInterval":60000,"Frames":[{"Type":"Death","Location":[8071,3473]},{"Type":"Kill","Location":[13121,2154]},{"Type":"Kill","Location":[12554,1501]},{"Type":"Kill","Location":[4863,11641]},{"Type":"Death","Location":[3153,11617]},{"Type":"Kill","Location":[12412,5080]},{"Type":"Kill","Location":[11173,5013]},{"Type":"Kill","Location":[13958,5287]},{"Type":"Death","Location":[13543,4360]},{"Type":"Kill","Location":[5128,9521]},{"Type":"Kill","Location":[3217,10883]},{"Type":"Death","Location":[3408,11162]},{"Type":"Kill","Location":[7475,13420]},{"Type":"Death","Location":[13843,4003]},{"Type":"Death","Location":[8029,6483]}]},{"MatchID":2101508868,"Lane":"TOP","Role":"SOLO","FrameInterval":60000,"Frames":[{"Type":"Kill","Location":[1307,11144]},{"Type":"Kill","Location":[13079,3819]},{"Type":"Death","Location":[13562,4486]},{"Type":"Kill","Location":[3060,10192]},{"Type":"Kill","Location":[762,10824]},{"Type":"Kill","Location":[13678,3467]},{"Type":"Kill","Location":[12059,2106]},{"Type":"Kill","Location":[4741,13808]},{"Type":"Kill","Location":[706,6844]},{"Type":"Kill","Location":[1195,4955]},{"Type":"Kill","Location":[7761,7665]},{"Type":"Kill","Location":[7385,7999]},{"Type":"Kill","Location":[4493,4500]}]},{"MatchID":2101661593,"Lane":"TOP","Role":"SOLO","FrameInterval":60000,"Frames":[{"Type":"Death","Location":[12269,1537]},{"Type":"Death","Location":[5325,13042]},{"Type":"Kill","Location":[13811,3447]},{"Type":"Kill","Location":[13012,3510]},{"Type":"Kill","Location":[1551,6935]},{"Type":"Death","Location":[3537,9229]},{"Type":"Death","Location":[6024,2290]},{"Type":"Death","Location":[5939,5432]},{"Type":"Death","Location":[8951,8282]},{"Type":"Kill","Location":[6226,10339]},{"Type":"Kill","Location":[12435,5919]},{"Type":"Death","Location":[7867,7898]},{"Type":"Kill","Location":[11396,10548]},{"Type":"Death","Location":[10226,10645]},{"Type":"Kill","Location":[14112,7026]},{"Type":"Kill","Location":[6055,5898]},{"Type":"Death","Location":[5916,6079]},{"Type":"Death","Location":[5126,9484]}]},{"MatchID":2101688346,"Lane":"TOP","Role":"SOLO","FrameInterval":60000,"Frames":[{"Type":"Death","Location":[2654,11534]},{"Type":"Kill","Location":[2506,11707]},{"Type":"Kill","Location":[4297,13641]},{"Type":"Kill","Location":[1579,8608]},{"Type":"Death","Location":[2758,12552]},{"Type":"Kill","Location":[8886,8412]},{"Type":"Kill","Location":[9147,9148]},{"Type":"Death","Location":[11113,3342]},{"Type":"Kill","Location":[10088,11374]},{"Type":"Kill","Location":[11519,12748]},{"Type":"Kill","Location":[9872,13790]},{"Type":"Kill","Location":[8728,792]},{"Type":"Death","Location":[12676,10381]},{"Type":"Death","Location":[8271,5794]},{"Type":"Kill","Location":[13338,12858]},{"Type":"Death","Location":[13701,13927]},{"Type":"Kill","Location":[9677,11874]},{"Type":"Kill","Location":[11349,12821]}]},{"MatchID":2101912777,"Lane":"TOP","Role":"SOLO","FrameInterval":60000,"Frames":[{"Type":"Kill","Location":[1906,11396]},{"Type":"Kill","Location":[5628,8456]},{"Type":"Kill","Location":[1482,10863]},{"Type":"Death","Location":[4635,13390]},{"Type":"Kill","Location":[1311,10071]},{"Type":"Death","Location":[1138,10284]},{"Type":"Kill","Location":[1670,8522]},{"Type":"Kill","Location":[5445,5264]},{"Type":"Death","Location":[3370,10922]},{"Type":"Kill","Location":[1749,11210]}]},{"MatchID":2103428357,"Lane":"TOP","Role":"SOLO","FrameInterval":60000,"Frames":[{"Type":"Death","Location":[2217,13204]},{"Type":"Death","Location":[1666,11939]},{"Type":"Kill","Location":[8616,8554]},{"Type":"Death","Location":[9068,8380]},{"Type":"Death","Location":[1254,10873]},{"Type":"Kill","Location":[5785,6047]},{"Type":"Kill","Location":[8607,3801]},{"Type":"Death","Location":[2649,6605]},{"Type":"Death","Location":[4016,7145]},{"Type":"Kill","Location":[6006,3970]},{"Type":"Death","Location":[4010,7167]},{"Type":"Death","Location":[4323,4525]}]},{"MatchID":2103676457,"Lane":"TOP","Role":"SOLO","FrameInterval":60000,"Frames":[{"Type":"Kill","Location":[13136,4198]},{"Type":"Kill","Location":[13102,3760]},{"Type":"Death","Location":[6760,3099]},{"Type":"Kill","Location":[10190,2389]},{"Type":"Death","Location":[9595,2400]},{"Type":"Death","Location":[2094,9788]},{"Type":"Kill","Location":[6315,11150]},{"Type":"Kill","Location":[7430,11618]},{"Type":"Kill","Location":[7004,7473]},{"Type":"Death","Location":[7437,1191]},{"Type":"Death","Location":[7073,9896]},{"Type":"Death","Location":[3176,10765]}]},{"MatchID":2103740385,"Lane":"TOP","Role":"SOLO","FrameInterval":60000,"Frames":[{"Type":"Death","Location":[2515,12997]},{"Type":"Death","Location":[1040,9541]},{"Type":"Death","Location":[3137,13483]},{"Type":"Death","Location":[9127,8484]},{"Type":"Kill","Location":[8062,2166]},{"Type":"Kill","Location":[2740,7504]},{"Type":"Kill","Location":[2604,6077]},{"Type":"Death","Location":[3185,5004]},{"Type":"Kill","Location":[13651,5570]},{"Type":"Kill","Location":[7839,1246]},{"Type":"Kill","Location":[7200,1230]},{"Type":"Kill","Location":[5774,13268]},{"Type":"Kill","Location":[4867,5788]},{"Type":"Kill","Location":[4928,4572]},{"Type":"Kill","Location":[2261,3338]},{"Type":"Kill","Location":[973,6677]},{"Type":"Kill","Location":[1306,8072]},{"Type":"Kill","Location":[1368,7238]},{"Type":"Death","Location":[12180,7256]}]},{"MatchID":2104560048,"Lane":"TOP","Role":"SOLO","FrameInterval":60000,"Frames":[{"Type":"Death","Location":[1372,10005]},{"Type":"Death","Location":[794,9983]},{"Type":"Kill","Location":[4373,5933]},{"Type":"Kill","Location":[9762,9595]},{"Type":"Death","Location":[9138,8355]},{"Type":"Kill","Location":[5301,10642]},{"Type":"Kill","Location":[8134,13846]},{"Type":"Kill","Location":[6121,10977]},{"Type":"Kill","Location":[13849,7404]},{"Type":"Kill","Location":[14010,7271]},{"Type":"Kill","Location":[13789,8300]},{"Type":"Kill","Location":[13462,6994]},{"Type":"Death","Location":[13699,7007]},{"Type":"Death","Location":[5008,14108]}]},{"MatchID":2104568702,"Lane":"TOP","Role":"SOLO","FrameInterval":60000,"Frames":[{"Type":"Death","Location":[2761,12305]},{"Type":"Death","Location":[2225,13362]},{"Type":"Kill","Location":[1917,12774]},{"Type":"Kill","Location":[8522,7529]},{"Type":"Kill","Location":[10030,5808]},{"Type":"Kill","Location":[7173,6968]},{"Type":"Kill","Location":[11020,11076]},{"Type":"Kill","Location":[11907,5544]},{"Type":"Kill","Location":[9490,9073]},{"Type":"Death","Location":[9612,8892]},{"Type":"Death","Location":[8938,13104]},{"Type":"Kill","Location":[9929,11018]},{"Type":"Death","Location":[10040,10154]}]},{"MatchID":2104642812,"Lane":"MIDDLE","Role":"SOLO","FrameInterval":60000,"Frames":[{"Type":"Death","Location":[4228,7195]},{"Type":"Kill","Location":[4964,11685]},{"Type":"Death","Location":[4069,11243]},{"Type":"Kill","Location":[9317,2003]},{"Type":"Kill","Location":[6883,6447]},{"Type":"Kill","Location":[8206,5567]},{"Type":"Death","Location":[11599,2972]},{"Type":"Kill","Location":[5651,756]},{"Type":"Kill","Location":[5622,756]},{"Type":"Death","Location":[3303,6246]},{"Type":"Kill","Location":[7076,1615]},{"Type":"Death","Location":[2808,2108]}]},{"MatchID":2104645195,"Lane":"TOP","Role":"SOLO","FrameInterval":60000,"Frames":[{"Type":"Death","Location":[13778,6480]},{"Type":"Death","Location":[946,11277]},{"Type":"Death","Location":[967,11944]},{"Type":"Death","Location":[1269,11147]},{"Type":"Death","Location":[820,10825]},{"Type":"Kill","Location":[4879,8355]},{"Type":"Death","Location":[3733,8239]},{"Type":"Death","Location":[3493,4169]},{"Type":"Kill","Location":[1295,779]},{"Type":"Kill","Location":[2503,844]}]},{"MatchID":2104668905,"Lane":"TOP","Role":"SOLO","FrameInterval":60000,"Frames":[{"Type":"Kill","Location":[5097,9254]},{"Type":"Kill","Location":[4692,14049]},{"Type":"Kill","Location":[7753,8246]},{"Type":"Death","Location":[3306,13755]},{"Type":"Death","Location":[11418,5916]},{"Type":"Kill","Location":[10398,882]},{"Type":"Kill","Location":[10146,854]},{"Type":"Kill","Location":[13645,3689]},{"Type":"Death","Location":[9972,8830]},{"Type":"Kill","Location":[4992,8758]},{"Type":"Kill","Location":[4986,9243]},{"Type":"Kill","Location":[6371,9373]},{"Type":"Kill","Location":[9759,10311]},{"Type":"Kill","Location":[9750,9540]},{"Type":"Death","Location":[6975,7064]},{"Type":"Kill","Location":[6269,4713]},{"Type":"Death","Location":[10735,1011]},{"Type":"Death","Location":[922,3389]},{"Type":"Kill","Location":[1160,3995]}]},{"MatchID":2104888231,"Lane":"TOP","Role":"SOLO","FrameInterval":60000,"Frames":[{"Type":"Death","Location":[8409,2309]},{"Type":"Kill","Location":[10420,7412]},{"Type":"Death","Location":[5126,5728]},{"Type":"Death","Location":[3758,9348]},{"Type":"Death","Location":[3418,2534]}]},{"MatchID":2105536128,"Lane":"TOP","Role":"SOLO","FrameInterval":60000,"Frames":[{"Type":"Death","Location":[835,10885]},{"Type":"Kill","Location":[8399,7792]},{"Type":"Death","Location":[1372,5826]},{"Type":"Kill","Location":[820,8338]},{"Type":"Death","Location":[1400,8354]},{"Type":"Death","Location":[4768,4457]},{"Type":"Kill","Location":[4528,6262]},{"Type":"Kill","Location":[4737,6830]},{"Type":"Kill","Location":[4581,4230]},{"Type":"Death","Location":[4862,4402]},{"Type":"Kill","Location":[2356,2618]},{"Type":"Death","Location":[2608,2674]}]},{"MatchID":2105537829,"Lane":"TOP","Role":"SOLO","FrameInterval":60000,"Frames":[{"Type":"Death","Location":[6953,13618]},{"Type":"Death","Location":[3713,13876]},{"Type":"Kill","Location":[10895,1118]},{"Type":"Kill","Location":[6398,6539]},{"Type":"Death","Location":[6970,13203]},{"Type":"Kill","Location":[1475,12676]},{"Type":"Kill","Location":[9946,1320]},{"Type":"Death","Location":[11990,3601]},{"Type":"Kill","Location":[1733,11352]},{"Type":"Death","Location":[11378,5783]},{"Type":"Kill","Location":[11255,10050]},{"Type":"Death","Location":[11716,9801]}]},{"MatchID":2105620127,"Lane":"TOP","Role":"SOLO","FrameInterval":60000,"Frames":[{"Type":"Death","Location":[1394,11330]},{"Type":"Death","Location":[3843,12959]},{"Type":"Death","Location":[2942,11894]},{"Type":"Kill","Location":[12455,2307]},{"Type":"Kill","Location":[13581,3013]},{"Type":"Kill","Location":[4172,14002]},{"Type":"Death","Location":[3885,12777]},{"Type":"Death","Location":[2892,12844]},{"Type":"Death","Location":[3851,12755]},{"Type":"Death","Location":[1327,7438]},{"Type":"Death","Location":[11841,3443]},{"Type":"Kill","Location":[1631,10978]},{"Type":"Death","Location":[12796,5362]},{"Type":"Kill","Location":[3678,8804]},{"Type":"Kill","Location":[9362,14021]}]},{"MatchID":2111229588,"Lane":"BOTTOM","Role":"DUO","FrameInterval":60000,"Frames":[{"Type":"Death","Location":[13439,4205]},{"Type":"Kill","Location":[11166,1692]},{"Type":"Kill","Location":[10364,953]},{"Type":"Death","Location":[9574,1646]},{"Type":"Death","Location":[14024,4824]},{"Type":"Kill","Location":[12126,5022]},{"Type":"Death","Location":[14068,5428]},{"Type":"Death","Location":[13153,10384]},{"Type":"Kill","Location":[13042,11567]}]},{"MatchID":2112289516,"Lane":"TOP","Role":"SOLO","FrameInterval":60000,"Frames":[{"Type":"Kill","Location":[3294,11063]},{"Type":"Death","Location":[3746,13072]},{"Type":"Kill","Location":[3811,11110]},{"Type":"Kill","Location":[6121,9004]},{"Type":"Death","Location":[4489,13933]},{"Type":"Kill","Location":[1390,6517]},{"Type":"Death","Location":[4562,7844]},{"Type":"Kill","Location":[7373,7686]},{"Type":"Kill","Location":[1284,12338]},{"Type":"Kill","Location":[4255,11436]},{"Type":"Kill","Location":[3172,10940]},{"Type":"Kill","Location":[4122,7808]},{"Type":"Kill","Location":[2830,3289]},{"Type":"Kill","Location":[3499,3086]}]},{"MatchID":2112364674,"Lane":"TOP","Role":"SOLO","FrameInterval":60000,"Frames":[{"Type":"Kill","Location":[3780,10415]},{"Type":"Death","Location":[4847,9826]},{"Type":"Death","Location":[924,11388]},{"Type":"Kill","Location":[5202,13649]},{"Type":"Kill","Location":[8073,8497]},{"Type":"Death","Location":[8270,8648]},{"Type":"Kill","Location":[1204,12482]},{"Type":"Kill","Location":[3077,11108]},{"Type":"Kill","Location":[3672,9482]},{"Type":"Death","Location":[4702,9295]},{"Type":"Death","Location":[8636,10268]},{"Type":"Death","Location":[13779,5478]},{"Type":"Death","Location":[11282,4242]},{"Type":"Death","Location":[4132,10368]},{"Type":"Kill","Location":[4872,8656]},{"Type":"Kill","Location":[4809,9756]},{"Type":"Kill","Location":[4550,10259]},{"Type":"Kill","Location":[811,6459]},{"Type":"Death","Location":[1033,7375]},{"Type":"Death","Location":[3526,3810]},{"Type":"Kill","Location":[11630,14168]},{"Type":"Death","Location":[6918,10082]},{"Type":"Kill","Location":[9990,7788]}]},{"MatchID":2112439956,"Lane":"TOP","Role":"SOLO","FrameInterval":60000,"Frames":[{"Type":"Death","Location":[2530,12134]},{"Type":"Death","Location":[1227,12074]},{"Type":"Kill","Location":[4164,13453]},{"Type":"Death","Location":[5638,9028]},{"Type":"Death","Location":[4244,13704]},{"Type":"Kill","Location":[5268,8810]},{"Type":"Death","Location":[11336,3466]},{"Type":"Kill","Location":[4738,6434]},{"Type":"Death","Location":[4828,7450]},{"Type":"Death","Location":[4860,5478]},{"Type":"Kill","Location":[7836,6387]},{"Type":"Kill","Location":[8434,7819]},{"Type":"Death","Location":[2615,1581]}]},{"MatchID":2113219949,"Lane":"TOP","Role":"SOLO","FrameInterval":60000,"Frames":[{"Type":"Death","Location":[4617,8964]},{"Type":"Kill","Location":[3772,10078]},{"Type":"Kill","Location":[3783,6069]},{"Type":"Kill","Location":[4187,6113]},{"Type":"Kill","Location":[2777,12004]},{"Type":"Death","Location":[1494,12718]},{"Type":"Death","Location":[2056,12594]},{"Type":"Kill","Location":[5379,12520]},{"Type":"Kill","Location":[4130,14003]},{"Type":"Death","Location":[4910,8542]},{"Type":"Kill","Location":[2812,12380]},{"Type":"Kill","Location":[10220,9998]},{"Type":"Kill","Location":[13466,12326]}]},{"MatchID":2113227746,"Lane":"TOP","Role":"SOLO","FrameInterval":60000,"Frames":[{"Type":"Kill","Location":[1214,10606]},{"Type":"Death","Location":[4125,13074]},{"Type":"Death","Location":[11324,1090]},{"Type":"Kill","Location":[2075,7684]},{"Type":"Death","Location":[8893,13825]},{"Type":"Kill","Location":[6954,13191]}]},{"MatchID":2113268537,"Lane":"TOP","Role":"SOLO","FrameInterval":60000,"Frames":[{"Type":"Death","Location":[4154,13345]},{"Type":"Kill","Location":[11022,4296]},{"Type":"Death","Location":[11058,4485]},{"Type":"Death","Location":[1933,11558]},{"Type":"Death","Location":[6273,7092]}]},{"MatchID":2113324727,"Lane":"BOTTOM","Role":"DUO_CARRY","FrameInterval":60000,"Frames":[{"Type":"Death","Location":[12846,5332]},{"Type":"Death","Location":[9750,1422]},{"Type":"Kill","Location":[13729,3936]},{"Type":"Death","Location":[13424,3222]},{"Type":"Death","Location":[9547,5890]},{"Type":"Kill","Location":[13833,4319]},{"Type":"Kill","Location":[13902,4775]},{"Type":"Death","Location":[3695,12795]},{"Type":"Kill","Location":[11188,14086]},{"Type":"Death","Location":[12875,13319]},{"Type":"Death","Location":[12604,7313]},{"Type":"Kill","Location":[5098,10580]},{"Type":"Kill","Location":[7438,9066]}]},{"MatchID":2113349722,"Lane":"TOP","Role":"SOLO","FrameInterval":60000,"Frames":[{"Type":"Kill","Location":[8407,819]},{"Type":"Kill","Location":[6627,1721]},{"Type":"Death","Location":[7319,1061]},{"Type":"Kill","Location":[1176,10532]},{"Type":"Kill","Location":[8542,4694]},{"Type":"Death","Location":[1351,11747]},{"Type":"Kill","Location":[1138,9082]},{"Type":"Kill","Location":[13288,3666]},{"Type":"Kill","Location":[762,6616]},{"Type":"Kill","Location":[10230,1438]},{"Type":"Kill","Location":[6550,3180]},{"Type":"Kill","Location":[3744,1292]},{"Type":"Death","Location":[2418,787]},{"Type":"Kill","Location":[5868,4250]},{"Type":"Kill","Location":[4734,5877]},{"Type":"Death","Location":[5638,5080]},{"Type":"Death","Location":[2816,5340]}]},{"MatchID":2113404578,"Lane":"TOP","Role":"SOLO","FrameInterval":60000,"Frames":[{"Type":"Kill","Location":[1908,11406]},{"Type":"Kill","Location":[1651,10762]},{"Type":"Death","Location":[1549,11557]},{"Type":"Kill","Location":[1586,11267]},{"Type":"Kill","Location":[13389,3301]},{"Type":"Kill","Location":[1194,6724]},{"Type":"Death","Location":[807,8074]},{"Type":"Kill","Location":[6360,3244]},{"Type":"Kill","Location":[6759,1406]}]},{"MatchID":2113409430,"Lane":"TOP","Role":"SOLO","FrameInterval":60000,"Frames":[{"Type":"Death","Location":[1137,10690]},{"Type":"Death","Location":[4351,9722]},{"Type":"Kill","Location":[1711,9192]},{"Type":"Kill","Location":[13203,4499]},{"Type":"Death","Location":[10845,7543]},{"Type":"Kill","Location":[1335,6718]},{"Type":"Death","Location":[6806,13108]},{"Type":"Kill","Location":[9294,1215]},{"Type":"Death","Location":[12999,2833]},{"Type":"Kill","Location":[1324,6676]},{"Type":"Kill","Location":[5538,987]}]},{"MatchID":2114085424,"Lane":"TOP","Role":"SOLO","FrameInterval":60000,"Frames":[{"Type":"Kill","Location":[5780,6554]},{"Type":"Kill","Location":[4956,5533]},{"Type":"Kill","Location":[7397,2645]},{"Type":"Kill","Location":[3930,4388]},{"Type":"Kill","Location":[3432,3575]}]},{"MatchID":2114145932,"Lane":"TOP","Role":"SOLO","FrameInterval":60000,"Frames":[{"Type":"Kill","Location":[1408,10895]},{"Type":"Kill","Location":[3302,7299]},{"Type":"Death","Location":[3139,9343]},{"Type":"Kill","Location":[2832,9623]},{"Type":"Death","Location":[8626,3473]},{"Type":"Death","Location":[4142,11385]},{"Type":"Death","Location":[7316,7216]},{"Type":"Death","Location":[2055,7677]},{"Type":"Kill","Location":[2020,3144]},{"Type":"Death","Location":[2184,3434]}]},{"MatchID":2114210125,"Lane":"TOP","Role":"SOLO","FrameInterval":60000,"Frames":[{"Type":"Death","Location":[1140,11023]},{"Type":"Death","Location":[2032,11624]},{"Type":"Death","Location":[2220,9858]},{"Type":"Death","Location":[4787,3859]},{"Type":"Death","Location":[5899,6257]}]},{"MatchID":2114233808,"Lane":"TOP","Role":"SOLO","FrameInterval":60000,"Frames":[{"Type":"Kill","Location":[2990,12594]},{"Type":"Kill","Location":[4317,11905]},{"Type":"Death","Location":[5254,12347]},{"Type":"Kill","Location":[4097,13644]},{"Type":"Kill","Location":[13780,8512]},{"Type":"Death","Location":[9180,13144]},{"Type":"Death","Location":[6922,11398]},{"Type":"Kill","Location":[9078,13667]},{"Type":"Kill","Location":[12571,7243]},{"Type":"Kill","Location":[13476,10696]}]},{"MatchID":2115904325,"Lane":"TOP","Role":"SOLO","FrameInterval":60000,"Frames":[{"Type":"Kill","Location":[3318,13704]},{"Type":"Kill","Location":[4338,13708]},{"Type":"Kill","Location":[13981,5338]},{"Type":"Kill","Location":[7068,13335]},{"Type":"Kill","Location":[13197,3929]},{"Type":"Kill","Location":[13176,3488]},{"Type":"Death","Location":[12848,3156]},{"Type":"Kill","Location":[8766,8440]},{"Type":"Kill","Location":[9007,9216]},{"Type":"Kill","Location":[9606,9237]},{"Type":"Kill","Location":[10230,10107]},{"Type":"Kill","Location":[11801,14158]},{"Type":"Kill","Location":[12557,12962]},{"Type":"Death","Location":[12592,12639]}]},{"MatchID":2116040544,"Lane":"TOP","Role":"SOLO","FrameInterval":60000,"Frames":[{"Type":"Kill","Location":[784,10352]},{"Type":"Death","Location":[977,10786]},{"Type":"Kill","Location":[5887,11131]},{"Type":"Kill","Location":[1112,10616]},{"Type":"Kill","Location":[1035,11966]},{"Type":"Kill","Location":[5623,6488]},{"Type":"Kill","Location":[5136,4950]},{"Type":"Kill","Location":[2905,5029]},{"Type":"Kill","Location":[3043,2651]},{"Type":"Death","Location":[2947,2762]}]},{"MatchID":2116128368,"Lane":"TOP","Role":"SOLO","FrameInterval":60000,"Frames":[{"Type":"Death","Location":[779,10354]},{"Type":"Death","Location":[2048,13160]},{"Type":"Death","Location":[11502,4353]},{"Type":"Death","Location":[1617,8508]},{"Type":"Kill","Location":[3429,11434]},{"Type":"Kill","Location":[5794,7530]},{"Type":"Kill","Location":[6796,6995]},{"Type":"Kill","Location":[5058,7740]},{"Type":"Death","Location":[1147,7949]},{"Type":"Death","Location":[897,10664]}]},{"MatchID":2116185860,"Lane":"TOP","Role":"SOLO","FrameInterval":60000,"Frames":[{"Type":"Kill","Location":[3403,10600]},{"Type":"Kill","Location":[12706,3169]},{"Type":"Kill","Location":[7004,893]},{"Type":"Death","Location":[14064,8578]},{"Type":"Kill","Location":[5976,5518]},{"Type":"Kill","Location":[4695,9830]},{"Type":"Kill","Location":[1782,2955]},{"Type":"Kill","Location":[592,1683]}]},{"MatchID":2116247466,"Lane":"TOP","Role":"SOLO","FrameInterval":60000,"Frames":[{"Type":"Death","Location":[1060,10091]},{"Type":"Kill","Location":[13223,3801]},{"Type":"Kill","Location":[1319,11650]},{"Type":"Death","Location":[13493,7304]},{"Type":"Kill","Location":[9430,11762]},{"Type":"Kill","Location":[13870,12773]}]},{"MatchID":2116296542,"Lane":"TOP","Role":"SOLO","FrameInterval":60000,"Frames":[{"Type":"Kill","Location":[7721,7595]},{"Type":"Death","Location":[4791,9627]},{"Type":"Death","Location":[2989,12304]},{"Type":"Kill","Location":[1628,10696]},{"Type":"Death","Location":[3270,11612]},{"Type":"Death","Location":[4521,12242]},{"Type":"Kill","Location":[6140,9770]},{"Type":"Death","Location":[6767,9454]},{"Type":"Kill","Location":[3594,9668]}]},{"MatchID":2116375533,"Lane":"TOP","Role":"SOLO","FrameInterval":60000,"Frames":[{"Type":"Death","Location":[1200,11263]},{"Type":"Kill","Location":[2891,12822]},{"Type":"Kill","Location":[13366,6712]},{"Type":"Death","Location":[7323,7307]},{"Type":"Kill","Location":[9793,9829]},{"Type":"Kill","Location":[10212,9554]},{"Type":"Kill","Location":[9162,9737]},{"Type":"Kill","Location":[9589,9439]}]},{"MatchID":2116413834,"Lane":"TOP","Role":"SOLO","FrameInterval":60000,"Frames":[{"Type":"Death","Location":[4644,13931]},{"Type":"Death","Location":[3540,13380]},{"Type":"Death","Location":[4538,13874]},{"Type":"Death","Location":[13948,4035]},{"Type":"Kill","Location":[814,9367]},{"Type":"Kill","Location":[7219,7288]},{"Type":"Kill","Location":[6375,8097]},{"Type":"Death","Location":[2095,9780]},{"Type":"Kill","Location":[6015,10277]},{"Type":"Kill","Location":[6184,8302]},{"Type":"Death","Location":[5422,10708]},{"Type":"Kill","Location":[13876,6986]},{"Type":"Kill","Location":[2120,9534]},{"Type":"Kill","Location":[3379,8451]}]},{"MatchID":2116484106,"Lane":"TOP","Role":"SOLO","FrameInterval":60000,"Frames":[{"Type":"Death","Location":[4256,14051]},{"Type":"Kill","Location":[3729,13065]},{"Type":"Death","Location":[3198,13788]},{"Type":"Death","Location":[1357,12575]},{"Type":"Kill","Location":[12593,3156]},{"Type":"Kill","Location":[12596,2795]},{"Type":"Death","Location":[13605,3184]},{"Type":"Kill","Location":[6615,7473]},{"Type":"Death","Location":[13685,4553]},{"Type":"Death","Location":[3680,10439]},{"Type":"Death","Location":[14069,7069]},{"Type":"Death","Location":[9857,13333]},{"Type":"Kill","Location":[8956,9596]},{"Type":"Death","Location":[10464,11091]}]},{"MatchID":2116547632,"Lane":"TOP","Role":"SOLO","FrameInterval":60000,"Frames":[{"Type":"Death","Location":[3940,12996]},{"Type":"Kill","Location":[4175,13906]},{"Type":"Death","Location":[2636,13311]},{"Type":"Kill","Location":[13864,3570]},{"Type":"Kill","Location":[3513,4285]},{"Type":"Death","Location":[7216,7460]},{"Type":"Kill","Location":[9314,8588]},{"Type":"Death","Location":[14098,7394]},{"Type":"Kill","Location":[1068,12252]},{"Type":"Death","Location":[13691,8536]}]},{"MatchID":2116601595,"Lane":"TOP","Role":"SOLO","FrameInterval":60000,"Frames":[{"Type":"Kill","Location":[2322,12718]},{"Type":"Kill","Location":[752,10572]},{"Type":"Kill","Location":[722,8546]},{"Type":"Kill","Location":[5404,6278]},{"Type":"Death","Location":[8467,8292]},{"Type":"Kill","Location":[7908,8058]},{"Type":"Kill","Location":[7910,6918]},{"Type":"Kill","Location":[8515,5153]},{"Type":"Death","Location":[4805,5986]},{"Type":"Kill","Location":[2442,4694]},{"Type":"Kill","Location":[4284,9586]},{"Type":"Kill","Location":[4499,10005]},{"Type":"Kill","Location":[1842,2049]},{"Type":"Death","Location":[2484,2358]},{"Type":"Kill","Location":[11034,7650]},{"Type":"Death","Location":[1727,1998]},{"Type":"Kill","Location":[9616,5538]}]},{"MatchID":2116608299,"Lane":"TOP","Role":"SOLO","FrameInterval":60000,"Frames":[{"Type":"Kill","Location":[4804,13690]},{"Type":"Kill","Location":[4173,13863]},{"Type":"Death","Location":[1281,10625]},{"Type":"Kill","Location":[11928,2325]},{"Type":"Death","Location":[12540,1552]},{"Type":"Kill","Location":[1544,12242]},{"Type":"Death","Location":[5224,12411]},{"Type":"Death","Location":[11719,4506]},{"Type":"Kill","Location":[7437,7586]}]},{"MatchID":2117068020,"Lane":"TOP","Role":"SOLO","FrameInterval":60000,"Frames":[{"Type":"Death","Location":[5956,12741]},{"Type":"Kill","Location":[11411,1743]},{"Type":"Death","Location":[9517,3310]},{"Type":"Kill","Location":[2826,11700]},{"Type":"Kill","Location":[1561,11408]},{"Type":"Kill","Location":[4970,6110]},{"Type":"Death","Location":[5932,5128]},{"Type":"Death","Location":[2124,1183]}]},{"MatchID":2117185946,"Lane":"BOTTOM","Role":"DUO_CARRY","FrameInterval":60000,"Frames":[{"Type":"Kill","Location":[13588,3131]},{"Type":"Death","Location":[13779,3125]},{"Type":"Kill","Location":[10959,916]},{"Type":"Kill","Location":[12009,1908]},{"Type":"Death","Location":[10938,1364]},{"Type":"Death","Location":[6556,6729]},{"Type":"Death","Location":[13602,2686]},{"Type":"Death","Location":[6591,9161]},{"Type":"Death","Location":[10541,10354]},{"Type":"Death","Location":[7286,12527]},{"Type":"Kill","Location":[12843,10307]},{"Type":"Death","Location":[13296,10713]}]},{"MatchID":2117326886,"Lane":"TOP","Role":"SOLO","FrameInterval":60000,"Frames":[{"Type":"Death","Location":[10968,1407]},{"Type":"Death","Location":[2736,11930]}]},{"MatchID":2118317790,"Lane":"TOP","Role":"SOLO","FrameInterval":60000,"Frames":[{"Type":"Death","Location":[13842,3187]},{"Type":"Death","Location":[4745,11933]},{"Type":"Kill","Location":[2846,12552]},{"Type":"Death","Location":[7009,6285]},{"Type":"Kill","Location":[4828,5612]},{"Type":"Kill","Location":[2818,1906]}]},{"MatchID":2118377418,"Lane":"TOP","Role":"SOLO","FrameInterval":60000,"Frames":[{"Type":"Death","Location":[2115,11783]},{"Type":"Kill","Location":[3900,13268]},{"Type":"Death","Location":[3612,13034]},{"Type":"Kill","Location":[13543,4116]},{"Type":"Kill","Location":[13293,3767]},{"Type":"Kill","Location":[12672,6394]},{"Type":"Kill","Location":[4696,13771]},{"Type":"Death","Location":[5156,11479]},{"Type":"Death","Location":[786,10362]},{"Type":"Death","Location":[10126,6893]},{"Type":"Kill","Location":[12050,12766]}]},{"MatchID":2118444374,"Lane":"TOP","Role":"SOLO","FrameInterval":60000,"Frames":[{"Type":"Death","Location":[2419,11869]},{"Type":"Death","Location":[7961,10041]},{"Type":"Kill","Location":[3818,7386]},{"Type":"Kill","Location":[10400,10388]},{"Type":"Kill","Location":[11977,10268]},{"Type":"Death","Location":[13607,11943]}]},{"MatchID":2118458336,"Lane":"TOP","Role":"SOLO","FrameInterval":60000,"Frames":[{"Type":"Death","Location":[1137,10775]},{"Type":"Death","Location":[9764,9969]},{"Type":"Death","Location":[13617,2793]},{"Type":"Kill","Location":[12669,11350]}]},{"MatchID":2126182148,"Lane":"TOP","Role":"SOLO","FrameInterval":60000,"Frames":[{"Type":"Kill","Location":[6927,13153]},{"Type":"Kill","Location":[7978,12338]},{"Type":"Kill","Location":[3907,12965]},{"Type":"Kill","Location":[6211,13941]},{"Type":"Kill","Location":[10273,2359]},{"Type":"Kill","Location":[12384,1369]},{"Type":"Death","Location":[14134,6744]},{"Type":"Kill","Location":[14068,6522]},{"Type":"Kill","Location":[4598,11558]},{"Type":"Death","Location":[4467,12322]},{"Type":"Kill","Location":[4196,9649]},{"Type":"Kill","Location":[10753,7593]},{"Type":"Kill","Location":[13545,11814]},{"Type":"Death","Location":[7422,7956]},{"Type":"Kill","Location":[6870,11580]},{"Type":"Kill","Location":[11553,12361]},{"Type":"Kill","Location":[13317,12782]}]},{"MatchID":2126261821,"Lane":"TOP","Role":"SOLO","FrameInterval":60000,"Frames":[{"Type":"Kill","Location":[3032,13286]},{"Type":"Kill","Location":[1529,9900]},{"Type":"Death","Location":[1514,10193]},{"Type":"Kill","Location":[1896,9571]},{"Type":"Kill","Location":[5237,13895]},{"Type":"Kill","Location":[4451,8308]},{"Type":"Kill","Location":[8326,13324]},{"Type":"Kill","Location":[14027,7167]},{"Type":"Kill","Location":[13202,14341]},{"Type":"Kill","Location":[13701,13858]}]},{"MatchID":2126875080,"Lane":"MIDDLE","Role":"SOLO","FrameInterval":60000,"Frames":[{"Type":"Kill","Location":[8297,8822]},{"Type":"Kill","Location":[6193,6479]},{"Type":"Kill","Location":[6119,5619]},{"Type":"Kill","Location":[5905,5735]},{"Type":"Death","Location":[5900,5712]},{"Type":"Death","Location":[5107,6045]},{"Type":"Kill","Location":[1438,10294]},{"Type":"Kill","Location":[11858,3089]},{"Type":"Death","Location":[11037,1189]},{"Type":"Death","Location":[1519,8564]},{"Type":"Death","Location":[10787,1625]},{"Type":"Kill","Location":[799,6703]},{"Type":"Kill","Location":[3778,762]},{"Type":"Kill","Location":[3823,826]}]},{"MatchID":2127406534,"Lane":"TOP","Role":"SOLO","FrameInterval":60000,"Frames":[{"Type":"Kill","Location":[2532,11831]},{"Type":"Kill","Location":[1176,12156]},{"Type":"Kill","Location":[7531,7225]},{"Type":"Kill","Location":[2564,12600]},{"Type":"Kill","Location":[7650,7253]},{"Type":"Kill","Location":[4225,14029]},{"Type":"Kill","Location":[5189,7548]},{"Type":"Kill","Location":[8129,8478]},{"Type":"Death","Location":[5842,14109]},{"Type":"Kill","Location":[7007,6315]},{"Type":"Kill","Location":[6909,6984]},{"Type":"Kill","Location":[6723,9936]},{"Type":"Death","Location":[7672,7905]},{"Type":"Kill","Location":[6220,10578]},{"Type":"Kill","Location":[8429,6918]},{"Type":"Death","Location":[7782,7271]},{"Type":"Kill","Location":[9858,10867]},{"Type":"Death","Location":[8376,12004]},{"Type":"Kill","Location":[13795,13277]},{"Type":"Kill","Location":[13079,7429]},{"Type":"Kill","Location":[14194,12475]},{"Type":"Kill","Location":[13876,13600]},{"Type":"Death","Location":[12294,12560]}]},{"MatchID":2127454274,"Lane":"TOP","Role":"SOLO","FrameInterval":60000,"Frames":[{"Type":"Death","Location":[1509,12174]},{"Type":"Death","Location":[4065,12223]},{"Type":"Death","Location":[3267,13394]},{"Type":"Kill","Location":[13620,5082]},{"Type":"Death","Location":[1377,12186]},{"Type":"Death","Location":[8688,11190]},{"Type":"Death","Location":[11681,7813]},{"Type":"Death","Location":[1174,12047]},{"Type":"Kill","Location":[14025,4902]},{"Type":"Kill","Location":[13972,6961]},{"Type":"Death","Location":[12018,1203]},{"Type":"Death","Location":[8919,9664]},{"Type":"Death","Location":[7344,6314]},{"Type":"Death","Location":[9760,7140]},{"Type":"Kill","Location":[10872,8206]},{"Type":"Kill","Location":[9998,8444]},{"Type":"Kill","Location":[13213,7074]},{"Type":"Death","Location":[13635,13330]},{"Type":"Kill","Location":[13948,12931]}]},{"MatchID":2127501301,"Lane":"TOP","Role":"SOLO","FrameInterval":60000,"Frames":[{"Type":"Kill","Location":[1039,10712]},{"Type":"Death","Location":[1086,10793]}]},{"MatchID":2127533073,"Lane":"TOP","Role":"SOLO","FrameInterval":60000,"Frames":[{"Type":"Death","Location":[1251,11304]},{"Type":"Kill","Location":[6892,11388]},{"Type":"Kill","Location":[12615,5529]},{"Type":"Kill","Location":[11923,5597]},{"Type":"Death","Location":[13061,4620]},{"Type":"Death","Location":[2179,13369]},{"Type":"Kill","Location":[8776,7768]},{"Type":"Kill","Location":[6007,6753]},{"Type":"Death","Location":[6841,7662]},{"Type":"Death","Location":[7024,11440]},{"Type":"Death","Location":[4033,3647]},{"Type":"Death","Location":[7277,926]},{"Type":"Kill","Location":[1408,6862]},{"Type":"Death","Location":[1681,7285]},{"Type":"Death","Location":[4577,9252]}]},{"MatchID":2128388165,"Lane":"TOP","Role":"SOLO","FrameInterval":60000,"Frames":[{"Type":"Kill","Location":[5888,13304]},{"Type":"Death","Location":[3941,13660]},{"Type":"Death","Location":[3993,13536]},{"Type":"Death","Location":[4630,13310]},{"Type":"Death","Location":[2389,13061]},{"Type":"Kill","Location":[4776,9830]},{"Type":"Death","Location":[4556,13335]},{"Type":"Kill","Location":[5278,5277]},{"Type":"Death","Location":[5799,5632]},{"Type":"Kill","Location":[2744,5878]},{"Type":"Kill","Location":[3867,7154]},{"Type":"Kill","Location":[4708,7769]},{"Type":"Death","Location":[5063,1447]},{"Type":"Death","Location":[6024,1678]},{"Type":"Death","Location":[5444,1558]},{"Type":"Death","Location":[2020,1652]},{"Type":"Kill","Location":[3558,8514]},{"Type":"Death","Location":[5323,10490]},{"Type":"Kill","Location":[4514,10097]},{"Type":"Kill","Location":[5053,10215]},{"Type":"Kill","Location":[3079,13600]}]},{"MatchID":2128494661,"Lane":"TOP","Role":"SOLO","FrameInterval":60000,"Frames":[{"Type":"Kill","Location":[794,10675]},{"Type":"Death","Location":[761,9236]},{"Type":"Kill","Location":[1300,11133]},{"Type":"Death","Location":[1659,11136]},{"Type":"Kill","Location":[762,10102]},{"Type":"Kill","Location":[1670,11344]},{"Type":"Kill","Location":[986,6867]},{"Type":"Kill","Location":[4414,6006]},{"Type":"Kill","Location":[4832,5621]},{"Type":"Kill","Location":[11102,9044]},{"Type":"Kill","Location":[1771,11114]},{"Type":"Death","Location":[1108,1245]},{"Type":"Kill","Location":[1541,6401]}]},{"MatchID":2128499933,"Lane":"TOP","Role":"SOLO","FrameInterval":60000,"Frames":[{"Type":"Death","Location":[2878,13076]},{"Type":"Death","Location":[3646,13188]},{"Type":"Kill","Location":[8901,895]},{"Type":"Kill","Location":[6023,4180]}]},{"MatchID":2128518173,"Lane":"TOP","Role":"SOLO","FrameInterval":60000,"Frames":[{"Type":"Death","Location":[3539,13408]},{"Type":"Death","Location":[2387,13393]},{"Type":"Kill","Location":[3547,11336]},{"Type":"Kill","Location":[10056,8643]},{"Type":"Kill","Location":[3046,12950]},{"Type":"Death","Location":[10079,8853]}]},{"MatchID":2128562144,"Lane":"TOP","Role":"SOLO","FrameInterval":60000,"Frames":[{"Type":"Kill","Location":[13322,2334]},{"Type":"Death","Location":[13169,2526]},{"Type":"Kill","Location":[11743,1794]},{"Type":"Death","Location":[8976,4653]},{"Type":"Kill","Location":[5192,4741]},{"Type":"Kill","Location":[4818,5977]},{"Type":"Kill","Location":[6678,1457]},{"Type":"Death","Location":[5925,934]},{"Type":"Kill","Location":[4680,9696]},{"Type":"Kill","Location":[9224,790]},{"Type":"Kill","Location":[9192,1497]},{"Type":"Kill","Location":[13410,3911]},{"Type":"Kill","Location":[2738,1453]},{"Type":"Death","Location":[4056,1616]}]},{"MatchID":2129240433,"Lane":"TOP","Role":"SOLO","FrameInterval":60000,"Frames":[{"Type":"Death","Location":[12082,6938]},{"Type":"Kill","Location":[5224,11356]},{"Type":"Death","Location":[5028,11618]},{"Type":"Death","Location":[9239,879]},{"Type":"Kill","Location":[9359,2501]},{"Type":"Kill","Location":[8744,13588]},{"Type":"Death","Location":[6111,5998]},{"Type":"Death","Location":[10515,5354]},{"Type":"Death","Location":[6580,7838]}]},{"MatchID":2129294305,"Lane":"TOP","Role":"SOLO","FrameInterval":60000,"Frames":[{"Type":"Kill","Location":[3064,12648]},{"Type":"Death","Location":[10921,5136]},{"Type":"Kill","Location":[3864,13219]},{"Type":"Death","Location":[13281,6672]},{"Type":"Death","Location":[6859,11534]},{"Type":"Kill","Location":[10967,3395]},{"Type":"Kill","Location":[8914,9169]},{"Type":"Kill","Location":[10104,5543]},{"Type":"Kill","Location":[8514,5180]},{"Type":"Kill","Location":[8536,5318]},{"Type":"Death","Location":[9269,6218]},{"Type":"Kill","Location":[13006,11036]},{"Type":"Death","Location":[13562,6440]},{"Type":"Kill","Location":[8003,6761]},{"Type":"Death","Location":[14114,10322]},{"Type":"Death","Location":[4251,11321]},{"Type":"Death","Location":[1739,10891]}]},{"MatchID":2130620217,"Lane":"TOP","Role":"SOLO","FrameInterval":60000,"Frames":[{"Type":"Death","Location":[1325,11071]},{"Type":"Death","Location":[1269,11029]},{"Type":"Kill","Location":[13110,1987]},{"Type":"Kill","Location":[13355,4035]},{"Type":"Death","Location":[10914,3304]},{"Type":"Death","Location":[1728,11206]},{"Type":"Death","Location":[978,11248]},{"Type":"Kill","Location":[7420,8470]},{"Type":"Death","Location":[8818,8960]},{"Type":"Death","Location":[10604,3192]},{"Type":"Death","Location":[2628,7091]},{"Type":"Death","Location":[666,1517]},{"Type":"Kill","Location":[5162,10260]},{"Type":"Kill","Location":[9417,9710]},{"Type":"Death","Location":[11214,4808]},{"Type":"Kill","Location":[10916,4798]},{"Type":"Death","Location":[12496,11558]}]},{"MatchID":2130656737,"Lane":"TOP","Role":"SOLO","FrameInterval":60000,"Frames":[{"Type":"Kill","Location":[4882,13925]},{"Type":"Death","Location":[6084,6094]},{"Type":"Kill","Location":[7768,12047]},{"Type":"Kill","Location":[6439,13597]},{"Type":"Death","Location":[1304,10083]},{"Type":"Death","Location":[9837,7207]},{"Type":"Kill","Location":[2435,11869]},{"Type":"Death","Location":[6124,10034]},{"Type":"Death","Location":[2842,13562]},{"Type":"Death","Location":[658,2243]},{"Type":"Kill","Location":[4819,4211]}]},{"MatchID":2137647975,"Lane":"TOP","Role":"SOLO","FrameInterval":60000,"Frames":[{"Type":"Death","Location":[4389,13727]},{"Type":"Kill","Location":[3223,8869]},{"Type":"Death","Location":[13891,3504]},{"Type":"Death","Location":[4089,13397]},{"Type":"Kill","Location":[8092,8388]},{"Type":"Death","Location":[8832,8926]}]},{"MatchID":2137703923,"Lane":"TOP","Role":"SOLO","FrameInterval":60000,"Frames":[{"Type":"Death","Location":[1295,10574]},{"Type":"Death","Location":[876,7076]},{"Type":"Kill","Location":[1297,9245]},{"Type":"Death","Location":[10300,1464]},{"Type":"Death","Location":[1806,11618]},{"Type":"Kill","Location":[11999,8924]},{"Type":"Kill","Location":[9868,9796]},{"Type":"Kill","Location":[13622,9516]},{"Type":"Kill","Location":[13983,10201]},{"Type":"Kill","Location":[13658,11824]},{"Type":"Death","Location":[11047,10545]},{"Type":"Death","Location":[8706,11215]}]}]